snapkit/__init__.py
snapkit/utils/__init__.py
snapkit/utils/cli/__init__.py
snapkit/utils/cli/cli_handler.py
snapkit/utils/modules/__init__.py
snapkit/utils/modules/jpg_to_png.py
snapkit/utils/modules/overlay.py
snapkit-0.0.2.dist-info/licenses/LICENSE
snapkit-0.0.2.dist-info/METADATA
snapkit-0.0.2.dist-info/WHEEL
snapkit-0.0.2.dist-info/entry_points.txt
snapkit-0.0.2.dist-info/top_level.txt
snapkit-0.0.2.dist-info/RECORD
