Metadata-Version: 2.4
Name: snapkit
Version: 0.0.2
Summary: SnapKit: Handy image utilities for AI/CV workflows
Home-page: https://github.com/mallickboy/snapkit
Author: Tamal Mallick
Author-email: contact@mallickboy.com
License: MIT
Classifier: Development Status :: 3 - Alpha
Classifier: Intended Audience :: Developers
Classifier: License :: OSI Approved :: MIT License
Classifier: Programming Language :: Python :: 3
Classifier: Topic :: Software Development :: Libraries :: Python Modules
Classifier: Topic :: Multimedia :: Graphics
License-File: LICENSE
Requires-Dist: Pillow
Requires-Dist: tqdm
Dynamic: author
Dynamic: author-email
Dynamic: classifier
Dynamic: description
Dynamic: description-content-type
Dynamic: home-page
Dynamic: license
Dynamic: license-file
Dynamic: requires-dist
Dynamic: summary
